{
  "project_info": {
    "project_number": "726001759582",
    "firebase_url": "https://tiktek-lior-sagi-default-rtdb.firebaseio.com",
    "project_id": "tiktek-lior-sagi",
    "storage_bucket": "tiktek-lior-sagi.firebasestorage.app"
  },
  "client": [
    {
      "client_info": {
        "mobilesdk_app_id": "1:726001759582:android:80f4dc4e55970f76cfcbcf",
        "android_client_info": {
          "package_name": "com.example.tiktek_lior_sagi"
        }
      },
      "oauth_client": [],
      "api_key": [
        {
          "current_key": "AIzaSyD-cuUGWXltDSMQHI7wBhZDvMnwz3m3LSY"
        }
      ],
      "services": {
        "appinvite_service": {
          "other_platform_oauth_client": []
        }
      }
    }
  ],
  "configuration_version": "1"
}